LICENSE.txt
MANIFEST.in
README.md
setup.py
snapml_auto_quantization/__init__.py
snapml_auto_quantization/brew_networks.py
snapml_auto_quantization/debug.py
snapml_auto_quantization/quant_adaptive_avg_pool.py
snapml_auto_quantization/quant_add.py
snapml_auto_quantization/quant_avgpool.py
snapml_auto_quantization/quant_base_module.py
snapml_auto_quantization/quant_concat.py
snapml_auto_quantization/quant_conv.py
snapml_auto_quantization/quant_deconv.py
snapml_auto_quantization/quant_flatten.py
snapml_auto_quantization/quant_layer_factory.py
snapml_auto_quantization/quant_leakyrelu.py
snapml_auto_quantization/quant_linear.py
snapml_auto_quantization/quant_maxpool.py
snapml_auto_quantization/quant_mean.py
snapml_auto_quantization/quant_mul.py
snapml_auto_quantization/quant_pad.py
snapml_auto_quantization/quant_permute.py
snapml_auto_quantization/quant_prelu.py
snapml_auto_quantization/quant_relu.py
snapml_auto_quantization/quant_reshape.py
snapml_auto_quantization/quant_resize.py
snapml_auto_quantization/quant_sigmoid.py
snapml_auto_quantization/quant_simulator.py
snapml_auto_quantization/quant_softmax.py
snapml_auto_quantization/quant_sub.py
snapml_auto_quantization/quant_utils.py
snapml_auto_quantization/quant_view.py
snapml_auto_quantization.egg-info/PKG-INFO
snapml_auto_quantization.egg-info/SOURCES.txt
snapml_auto_quantization.egg-info/dependency_links.txt
snapml_auto_quantization.egg-info/requires.txt
snapml_auto_quantization.egg-info/top_level.txt