Metadata-Version: 2.1
Name: snapml-auto-quantization
Version: 0.0.7
Summary: A automatic pipeline for SnapML quantization
Home-page: https://github.sc-corp.net/Snapchat/snapml_auto_quantization
Author: Jiazhuo Wang
Author-email: jwang7@snapchat.com
License: MIT
Platform: UNKNOWN
Requires-Python: >=3.6
License-File: LICENSE.txt
